snap_sort/__init__.py
snap_sort/cli.py
snap_sort/exposure.py
snap_sort/find_similar.py
snap_sort/redo.py
snap_sort/semantic.py
snap_sort/models/yolov8s.pt
snap_sort/utils/__init__.py
snap_sort/utils/cache_manager.py
snap_sort/utils/constants.py
snap_sort/utils/file_manager.py
snap_sort/utils/image_loader.py
cli_snapsort-1.0.0.dist-info/METADATA
cli_snapsort-1.0.0.dist-info/WHEEL
cli_snapsort-1.0.0.dist-info/entry_points.txt
cli_snapsort-1.0.0.dist-info/top_level.txt
cli_snapsort-1.0.0.dist-info/RECORD
