Metadata-Version: 2.1
Name: cli-snapsort
Version: 1.0.0
Summary: A CLI tool to classify photos
Home-page: https://github.com/Jiaaming/snapsort
Author: Jiaming Liu
Classifier: Programming Language :: Python :: 3
Classifier: License :: OSI Approved :: MIT License
Classifier: Operating System :: OS Independent
Requires-Python: >=3.8
Requires-Dist: click>=8.1.0
Requires-Dist: numpy>=1.21.0
Requires-Dist: torch>=1.9.0
Requires-Dist: setuptools>=50.0.0
Requires-Dist: ultralytics>=8.0.0
Requires-Dist: transformers>=4.0.0
Requires-Dist: imagehash>=4.2.1
Requires-Dist: pillow>=8.3.0
Requires-Dist: opencv-python>=4.5.0
Requires-Dist: sentence-transformers>=3.3.0
Requires-Dist: faiss-cpu>=1.9.0
